[
{"MagazinId":1,"Autor":"ADAC","Titel":"ADAC Motorwelt","Gruppe":"Publikum","Sachgruppe":"Motorpresse","Exemplare":2},
{"MagazinId":2,"Autor":"Wort \u0026 Bild Verlag","Titel":"Apotheken-Umschau","Gruppe":"Kunden","Sachgruppe":"Apotheken/Medizin/Gesundheit","Exemplare":2},
{"MagazinId":3,"Autor":"wdv-Gruppe","Titel":"Bleibgesund","Gruppe":"Kunden","Sachgruppe":"Medizin/Gesundheit","Exemplare":2},
{"MagazinId":4,"Autor":"wdv-Gruppe","Titel":"bleibgesund 60","Gruppe":"Kunden","Sachgruppe":"Medizin/Gesundheit","Exemplare":2},
{"MagazinId":5,"Autor":"Bauer Media Group","Titel":"tv14","Gruppe":"Publikum","Sachgruppe":"Programmzeitschriften","Exemplare":2},
{"MagazinId":6,"Autor":"IG Metall","Titel":"metallzeitung","Gruppe":"Publikum","Sachgruppe":"Aktuelle Zeitschriften und Magazine","Exemplare":2},
{"MagazinId":7,"Autor":"ver.di","Titel":"ver.di PUBLIK","Gruppe":"Publikum","Sachgruppe":"Sonstige Zeitschriften National","Exemplare":2},
{"MagazinId":8,"Autor":"Funke Mediengruppe","Titel":"TV Digital","Gruppe":"Publikum","Sachgruppe":"Programmzeitschriften","Exemplare":2},
{"MagazinId":9,"Autor":"Gebr. Storck GmbH \u0026 Co. Verlags-oHG","Titel":"Ratgeber/Meine Apotheke","Gruppe":"Kunden","Sachgruppe":"Apotheken/Medizin/Gesundheit","Exemplare":2},
{"MagazinId":10,"Autor":"Wort \u0026 Bild Verlag","Titel":"Senioren Ratgeber","Gruppe":"Kunden","Sachgruppe":"Apotheken/Medizin/Gesundheit","Exemplare":2},
{"MagazinId":11,"Autor":"EDEKA Verlagsgesellschaft mbH","Titel":"Mit Liebe - Das Genussmagazin","Gruppe":"Kunden","Sachgruppe":"Lebensmittel/Kochen/Haushalt","Exemplare":2},
{"MagazinId":12,"Autor":"Hubert Burda Media","Titel":"Das Haus","Gruppe":"Publikum","Sachgruppe":"Wohn- und Gartenzeitschriften","Exemplare":2},
{"MagazinId":13,"Autor":"J.Fink Verlag GmbH \u0026 Co. KG","Titel":"Mein Eigenheim, Wohnen \u0026 Leben","Gruppe":"Publikum","Sachgruppe":"Wohn- und Gartenzeitschriften","Exemplare":2},
{"MagazinId":14,"Autor":"Sozialverband VdK Deutschland","Titel":"VdK-Zeitung","Gruppe":"Publikum","Sachgruppe":"Aktuelle Zeitschriften und Magazine","Exemplare":2},
{"MagazinId":15,"Autor":"Wort \u0026 Bild Verlag","Titel":"medizini","Gruppe":"Kunden","Sachgruppe":"Apotheken/Medizin/Gesundheit","Exemplare":2},
{"MagazinId":16,"Autor":"BELLEVUE AND MORE GmbH","Titel":"Wohngl\u00FCck","Gruppe":"Publikum","Sachgruppe":"Wohn- und Gartenzeitschriften","Exemplare":2},
{"MagazinId":17,"Autor":"Wort \u0026 Bild Verlag","Titel":"Diabetes Ratgeber","Gruppe":"Kunden","Sachgruppe":"Apotheken/Medizin/Gesundheit","Exemplare":2},
{"MagazinId":18,"Autor":"Funke Mediengruppe","Titel":"TV Direkt","Gruppe":"Publikum","Sachgruppe":"Programmzeitschriften","Exemplare":2},
{"MagazinId":19,"Autor":"Bauer Media Group","Titel":"TV-Movie","Gruppe":"Publikum","Sachgruppe":"Programmzeitschriften","Exemplare":2},
{"MagazinId":20,"Autor":"Funke Mediengruppe","Titel":"H\u00F6rzu","Gruppe":"Publikum","Sachgruppe":"Programmzeitschriften","Exemplare":2},
{"MagazinId":21,"Autor":"wdv-Gruppe","Titel":"vigo Gesundheit - Das Kundenmagazin","Gruppe":"Kunden","Sachgruppe":"Medizin/Gesundheit","Exemplare":2},
{"MagazinId":22,"Autor":"Die Johanniter","Titel":"Johanniter","Gruppe":"Publikum","Sachgruppe":"Gesundheitsmagazine","Exemplare":2},
{"MagazinId":23,"Autor":"Arbeiter-Samariter-Bund Deutschland","Titel":"ASB Magazin","Gruppe":"Publikum","Sachgruppe":"Gesundheitsmagazine","Exemplare":2},
{"MagazinId":24,"Autor":"HMC Verlag Hamburg Media Company GmbH","Titel":"Wohnen - Das Magazin f\u00FCr Bauen, Einrichten \u0026 Lebensart","Gruppe":"Publikum","Sachgruppe":"Wohn- und Gartenzeitschriften","Exemplare":2},
{"MagazinId":25,"Autor":"Landwirtschaftsverlag M\u00FCnster","Titel":"Landlust \u2013 Die sch\u00F6nsten Seiten des Landlebens","Gruppe":"Publikum","Sachgruppe":"Wohn- und Gartenzeitschriften","Exemplare":2},
{"MagazinId":26,"Autor":"wdv-Gruppe","Titel":"on job","Gruppe":"Kunden","Sachgruppe":"Medizin/Gesundheit","Exemplare":2},
{"MagazinId":27,"Autor":"Bundesvereinigung Deutscher Apothekerverb\u00E4nde","Titel":"Neue Apotheken Illustrierte","Gruppe":"Kunden","Sachgruppe":"Apotheken/Medizin/Gesundheit","Exemplare":2},
{"MagazinId":28,"Autor":"Hubert Burda Media","Titel":"TV Spielfilm","Gruppe":"Publikum","Sachgruppe":"Programmzeitschriften","Exemplare":2},
{"MagazinId":29,"Autor":"Bauer Media Group","Titel":"Auf einen Blick","Gruppe":"Publikum","Sachgruppe":"Programmzeitschriften","Exemplare":2},
{"MagazinId":30,"Autor":"Bio Verlag GmbH","Titel":"Schrot \u0026 Korn Naturkostmagazin","Gruppe":"Kunden","Sachgruppe":"Lebensmittel","Exemplare":2},
{"MagazinId":31,"Autor":"SPIEGEL-Verlag","Titel":"Der Spiegel","Gruppe":"Publikum","Sachgruppe":"Aktuelle Zeitschriften und Magazine","Exemplare":2},
{"MagazinId":32,"Autor":"Funke Mediengruppe","Titel":"Bild der Frau","Gruppe":"Publikum","Sachgruppe":"W\u00F6chentliche Frauenzeitschriften","Exemplare":2},
{"MagazinId":33,"Autor":"Deutsches Jugendherbergswerk","Titel":"extra / tour","Gruppe":"Publikum","Sachgruppe":"Reisezeitschriften","Exemplare":2},
{"MagazinId":34,"Autor":"Hubert Burda Media","Titel":"Freizeit Revue","Gruppe":"Publikum","Sachgruppe":"W\u00F6chentliche Frauenzeitschriften","Exemplare":2},
{"MagazinId":35,"Autor":"Wort \u0026 Bild Verlag","Titel":"Baby und Familie","Gruppe":"Kunden","Sachgruppe":"Apotheken/Medizin/Gesundheit","Exemplare":2},
{"MagazinId":36,"Autor":"KONPRESS-Medien eG","Titel":"KONPRESS","Gruppe":"Publikum","Sachgruppe":"Konfessionelle Zeitschriften","Exemplare":2},
{"MagazinId":37,"Autor":"Gruner \u002B Jahr","Titel":"Stern","Gruppe":"Publikum","Sachgruppe":"Aktuelle Zeitschriften und Magazine","Exemplare":2},
{"MagazinId":38,"Autor":"","Titel":"JUNIOR Kinderzeitschriften","Gruppe":"Kunden","Sachgruppe":"Apotheken/Medizin/Gesundheit","Exemplare":2},
{"MagazinId":39,"Autor":"wdv-Gruppe","Titel":"on","Gruppe":"Kunden","Sachgruppe":"Medizin/Gesundheit","Exemplare":2},
{"MagazinId":40,"Autor":"Bauer Media Group","Titel":"TV H\u00F6ren und Sehen","Gruppe":"Publikum","Sachgruppe":"Programmzeitschriften","Exemplare":2},
{"MagazinId":41,"Autor":"Deutscher Mieterbund","Titel":"MieterZeitung","Gruppe":"Kunden","Sachgruppe":"Sonstige","Exemplare":2},
{"MagazinId":42,"Autor":"IG Bergbau, Chemie, Energie","Titel":"Kompakt","Gruppe":"Publikum","Sachgruppe":"Sonstige Zeitschriften National","Exemplare":2},
{"MagazinId":43,"Autor":"Deutscher Alpenverein","Titel":"DAV Panorama","Gruppe":"Publikum","Sachgruppe":"Sportzeitschriften","Exemplare":2},
{"MagazinId":44,"Autor":"Funke Mediengruppe","Titel":"NurTV","Gruppe":"Publikum","Sachgruppe":"Programmzeitschriften","Exemplare":2},
{"MagazinId":45,"Autor":"Bauer Media Group","Titel":"Neue Post","Gruppe":"Publikum","Sachgruppe":"W\u00F6chentliche Frauenzeitschriften","Exemplare":2},
{"MagazinId":46,"Autor":"Auto Club Europa","Titel":"ACE-Lenkrad","Gruppe":"Publikum","Sachgruppe":"Motorpresse","Exemplare":2},
{"MagazinId":47,"Autor":"Deutsche Verm\u00F6gensberatung","Titel":"Der Verm\u00F6gensberater","Gruppe":"Publikum","Sachgruppe":"Wirtschaftspresse","Exemplare":2},
{"MagazinId":48,"Autor":"Bauer Media Group","Titel":"tv pur","Gruppe":"Publikum","Sachgruppe":"Programmzeitschriften","Exemplare":2},
{"MagazinId":49,"Autor":"dbb beamtenbund und tarifunion","Titel":"DBB-Magazin","Gruppe":"Fach","Sachgruppe":"Recht und Verwaltung","Exemplare":2},
{"MagazinId":50,"Autor":"","Titel":"Fondsmagazin","Gruppe":"Kunden","Sachgruppe":"Finanzdienstleistungen","Exemplare":2},
{"MagazinId":51,"Autor":"Gruner \u002B Jahr","Titel":"Brigitte","Gruppe":"Publikum","Sachgruppe":"14-t\u00E4gliche Frauenzeitschriften","Exemplare":2},
{"MagazinId":52,"Autor":"","Titel":"rotkreuzmagazin f\u00FCr Mitglieder, Freunde und","Gruppe":"Publikum","Sachgruppe":"Gesundheitsmagazine","Exemplare":2},
{"MagazinId":53,"Autor":"Hubert Burda Media","Titel":"Bunte","Gruppe":"Publikum","Sachgruppe":"Aktuelle Zeitschriften und Magazine","Exemplare":2},
{"MagazinId":54,"Autor":"Hubert Burda Media","Titel":"Focus","Gruppe":"Publikum","Sachgruppe":"Aktuelle Zeitschriften und Magazine","Exemplare":2},
{"MagazinId":55,"Autor":"Wort \u0026 Bild Verlag","Titel":"HausArzt - PatientenMagazin","Gruppe":"Kunden","Sachgruppe":"Apotheken/Medizin/Gesundheit","Exemplare":2},
{"MagazinId":56,"Autor":"Katholische Frauengemeinschaft Deutschlands","Titel":"Frau und Mutter","Gruppe":"Publikum","Sachgruppe":"Monatliche Frauenzeitschriften","Exemplare":2},
{"MagazinId":57,"Autor":"Axel Springer","Titel":"Auto Bild","Gruppe":"Publikum","Sachgruppe":"Motorpresse","Exemplare":2},
{"MagazinId":58,"Autor":"mkv medienkontor Verlagsgesellschaft mbH \u0026 Co. KG","Titel":"mkv Apotheken-Kombi TV Gesund \u0026 Leben, LindaMagazin","Gruppe":"Kunden","Sachgruppe":"Apotheken/Medizin/Gesundheit","Exemplare":2},
{"MagazinId":59,"Autor":"Axel Springer","Titel":"Funk Uhr","Gruppe":"Publikum","Sachgruppe":"Programmzeitschriften","Exemplare":2},
{"MagazinId":60,"Autor":"TERRITORY CTR GmbH","Titel":"eve Magazin","Gruppe":"Kunden","Sachgruppe":"Lebensmittel","Exemplare":2},
{"MagazinId":61,"Autor":"Bauer Media Group","Titel":"Das Neue Blatt","Gruppe":"Publikum","Sachgruppe":"W\u00F6chentliche Frauenzeitschriften","Exemplare":2},
{"MagazinId":62,"Autor":"Bauer Media Group","Titel":"Freizeitwoche","Gruppe":"Publikum","Sachgruppe":"W\u00F6chentliche Frauenzeitschriften","Exemplare":2},
{"MagazinId":63,"Autor":"","Titel":"vigo GESUNDHEIT 65","Gruppe":"Kunden","Sachgruppe":"Medizin/Gesundheit","Exemplare":2},
{"MagazinId":64,"Autor":"","Titel":"SoVD Zeitung - Soziales im Blick","Gruppe":"Fach","Sachgruppe":"Sonstige","Exemplare":2},
{"MagazinId":65,"Autor":"Bauer Media Group","Titel":"Tina","Gruppe":"Publikum","Sachgruppe":"W\u00F6chentliche Frauenzeitschriften","Exemplare":2},
{"MagazinId":66,"Autor":"Reader\u2019s Digest Association","Titel":"Reader\u00B4s Digest Das Beste","Gruppe":"Publikum","Sachgruppe":"Aktuelle Zeitschriften und Magazine","Exemplare":2},
{"MagazinId":67,"Autor":"Sozialdemokratische Partei Deutschlands","Titel":"Vorw\u00E4rts","Gruppe":"Publikum","Sachgruppe":"Sonstige Zeitschriften National","Exemplare":2},
{"MagazinId":68,"Autor":"","Titel":"Meine Familie \u0026 ich","Gruppe":"Publikum","Sachgruppe":"Esszeitschriften","Exemplare":2},
{"MagazinId":69,"Autor":"Bauer Media Group","Titel":"Fernsehwoche","Gruppe":"Publikum","Sachgruppe":"Programmzeitschriften","Exemplare":2},
{"MagazinId":70,"Autor":"FUNKE Women Group GmbH","Titel":"Die Aktuelle","Gruppe":"Publikum","Sachgruppe":"W\u00F6chentliche Frauenzeitschriften","Exemplare":2},
{"MagazinId":71,"Autor":"Hubert Burda Media","Titel":"Freundin","Gruppe":"Publikum","Sachgruppe":"14-t\u00E4gliche Frauenzeitschriften","Exemplare":2},
{"MagazinId":72,"Autor":"Axel Springer","Titel":"Sport Bild","Gruppe":"Publikum","Sachgruppe":"Sportzeitschriften","Exemplare":2},
{"MagazinId":73,"Autor":"","Titel":"Familienheim und Garten","Gruppe":"Fach","Sachgruppe":"Freizeit und Hobby","Exemplare":2},
{"MagazinId":74,"Autor":"Hubert Burda Media","Titel":"InStyle","Gruppe":"Publikum","Sachgruppe":"Monatliche Frauenzeitschriften","Exemplare":2},
{"MagazinId":75,"Autor":"Hubert Burda Media","Titel":"Freizeit Spass","Gruppe":"Publikum","Sachgruppe":"W\u00F6chentliche Frauenzeitschriften","Exemplare":2},
{"MagazinId":76,"Autor":"Motor Presse Stuttgart","Titel":"auto motor und sport","Gruppe":"Publikum","Sachgruppe":"Motorpresse","Exemplare":2},
{"MagazinId":77,"Autor":"Deutscher \u00C4rzte-Verlag","Titel":"Deutsches \u00C4rzteblatt","Gruppe":"Fach","Sachgruppe":"Medizin und Gesundheitswesen","Exemplare":2},
{"MagazinId":78,"Autor":"Axel Springer Vertriebsservice GmbH","Titel":"Laviva","Gruppe":"Publikum","Sachgruppe":"Monatliche Frauenzeitschriften","Exemplare":2},
{"MagazinId":79,"Autor":"","Titel":"mein sch\u00F6nes Land","Gruppe":"Publikum","Sachgruppe":"Wohn- und Gartenzeitschriften","Exemplare":2},
{"MagazinId":80,"Autor":"Axel Springer","Titel":"Computer Bild","Gruppe":"Publikum","Sachgruppe":"IT-/Telekommunikationszeitschriften","Exemplare":2},
{"MagazinId":81,"Autor":"Gong Verlag","Titel":"TV f\u00FCr mich","Gruppe":"Publikum","Sachgruppe":"Programmzeitschriften","Exemplare":2},
{"MagazinId":82,"Autor":"","Titel":"Lufthansa Magazin Exclusive","Gruppe":"Kunden","Sachgruppe":"Reisen/Verkehrsgesellschaften","Exemplare":2},
{"MagazinId":83,"Autor":"Gruner \u002B Jahr","Titel":"Gala","Gruppe":"Publikum","Sachgruppe":"Aktuelle Zeitschriften und Magazine","Exemplare":2},
{"MagazinId":84,"Autor":"Cond\u00E9 Nast Verlag","Titel":"Glamour","Gruppe":"Publikum","Sachgruppe":"Monatliche Frauenzeitschriften","Exemplare":2},
{"MagazinId":85,"Autor":"Hubert Burda Media","Titel":"SUPERillu","Gruppe":"Publikum","Sachgruppe":"Aktuelle Zeitschriften und Magazine","Exemplare":2},
{"MagazinId":86,"Autor":"","Titel":"Gartenfreund/Siedlung und Eigenheim","Gruppe":"Publikum","Sachgruppe":"Wohn- und Gartenzeitschriften","Exemplare":2},
{"MagazinId":87,"Autor":"NABU Media-Agentur","Titel":"Naturschutz heute","Gruppe":"Publikum","Sachgruppe":"Naturzeitschriften","Exemplare":2},
{"MagazinId":88,"Autor":"Jahreszeiten Verlag","Titel":"F\u00FCr Sie","Gruppe":"Publikum","Sachgruppe":"14-t\u00E4gliche Frauenzeitschriften","Exemplare":2},
{"MagazinId":89,"Autor":"","Titel":"Deutsches \u00C4rzteblatt Kombi Praxis/Klinik","Gruppe":"Fach","Sachgruppe":"Medizin und Gesundheitswesen","Exemplare":2},
{"MagazinId":90,"Autor":"Hubert Burda Media","Titel":"Mein sch\u00F6ner Garten","Gruppe":"Publikum","Sachgruppe":"Wohn- und Gartenzeitschriften","Exemplare":2},
{"MagazinId":91,"Autor":"Hubert Burda Media","Titel":"TV Today","Gruppe":"Publikum","Sachgruppe":"Programmzeitschriften","Exemplare":2},
{"MagazinId":92,"Autor":"wdv-Gruppe","Titel":"on uni","Gruppe":"Kunden","Sachgruppe":"Medizin/Gesundheit","Exemplare":2},
{"MagazinId":93,"Autor":"Bauer Media Group","Titel":"Cosmopolitan","Gruppe":"Publikum","Sachgruppe":"Monatliche Frauenzeitschriften","Exemplare":2},
{"MagazinId":94,"Autor":"Funke Mediengruppe","Titel":"Land IDEE","Gruppe":"Publikum","Sachgruppe":"Wohn- und Gartenzeitschriften","Exemplare":2},
{"MagazinId":95,"Autor":"Hubert Burda Media","Titel":"Frau im Trend","Gruppe":"Publikum","Sachgruppe":"W\u00F6chentliche Frauenzeitschriften","Exemplare":2},
{"MagazinId":96,"Autor":"Heise Zeitschriften Verlag","Titel":"c\u0027t magazin f\u00FCr computertechnik","Gruppe":"Publikum","Sachgruppe":"IT-/Telekommunikationszeitschriften","Exemplare":2},
{"MagazinId":97,"Autor":"Junior-Verlag GmbH \u0026 Co. KG (Hamburg)","Titel":"kinder!","Gruppe":"Publikum","Sachgruppe":"Elternzeitschriften","Exemplare":2},
{"MagazinId":98,"Autor":"","Titel":"TV piccolino plus \u002B (TV piccolino\u002BTV Genie\u002BMy TV)","Gruppe":"Publikum","Sachgruppe":"Programmzeitschriften","Exemplare":2},
{"MagazinId":99,"Autor":"STAMM Verlag GmbH","Titel":"Erziehung und Wissenschaft","Gruppe":"Fach","Sachgruppe":"Erziehung und Bildung","Exemplare":2},
{"MagazinId":100,"Autor":"","Titel":"ACV Profil","Gruppe":"Publikum","Sachgruppe":"Motorpresse","Exemplare":2}]